BaseAzure/account.py
BaseAzure/app_service.py
BaseAzure/blob.py
BaseAzure/container.py
BaseAzure/data_factory.py
BaseAzure/dataset_blob.py
BaseAzure/dataset_db.py
BaseAzure/db.py
BaseAzure/helper.py
BaseAzure/lb.py
BaseAzure/linked_service_blob.py
BaseAzure/linked_service_db.py
BaseAzure/nat_gateway.py
BaseAzure/pipeline.py
BaseAzure/resource_group.py
BaseAzure/security_group.py
BaseAzure/ssis-ir.py
BaseAzure/vm.py
BaseAzure/vn.py
BaseAzure/vnp.py
Xby2Azure-1.0.4.dist-info/LICENSE
Xby2Azure-1.0.4.dist-info/METADATA
Xby2Azure-1.0.4.dist-info/WHEEL
Xby2Azure-1.0.4.dist-info/entry_points.txt
Xby2Azure-1.0.4.dist-info/top_level.txt
Xby2Azure-1.0.4.dist-info/RECORD
