Metadata-Version: 2.1
Name: Xby2Azure
Version: 1.0.4
Summary: Allows for the creation of custom pulumi resources.
Author-email: Collin Whitlow <cwhitlow@xby2.com>
License: Copyright 2022 X by 2        
Keywords: pulumi,xby2,azure
Classifier: License :: OSI Approved :: MIT License
Classifier: Programming Language :: Python
Classifier: Programming Language :: Python :: 3
Requires-Python: >=3.8
License-File: LICENSE
Requires-Dist: pulumi (<4.0.0,>=3.0.0)
Requires-Dist: pulumi-azure-native (<2.0.0,>=1.0.0)
Requires-Dist: pulumi-azure
